<?xml version="1.0"?>
<ROWSET>
 <ROW>
  <SHOP_ID>1</SHOP_ID>
  <PHONE_NUMBER>+55 (730) 255-8073</PHONE_NUMBER>
  <SHOP_NAME>FINALSALE.pl</SHOP_NAME>
 </ROW>
 <ROW>
  <SHOP_ID>2</SHOP_ID>
  <PHONE_NUMBER>+7 (624) 631-0537</PHONE_NUMBER>
  <SHOP_NAME>PRIMAMODA</SHOP_NAME>
 </ROW>
 <ROW>
  <SHOP_ID>3</SHOP_ID>
  <PHONE_NUMBER>+27 (830) 675-6567</PHONE_NUMBER>
  <SHOP_NAME>INGLOT</SHOP_NAME>
 </ROW>
 <ROW>
  <SHOP_ID>4</SHOP_ID>
  <PHONE_NUMBER>+55 (701) 607-0430</PHONE_NUMBER>
  <SHOP_NAME>GATTA</SHOP_NAME>
 </ROW>
 <ROW>
  <SHOP_ID>5</SHOP_ID>
  <PHONE_NUMBER>+62 (373) 557-9862</PHONE_NUMBER>
  <SHOP_NAME>WOJAS</SHOP_NAME>
 </ROW>
 <ROW>
  <SHOP_ID>6</SHOP_ID>
  <PHONE_NUMBER>+86 (979) 568-8193</PHONE_NUMBER>
  <SHOP_NAME>MAGIC OUTLET</SHOP_NAME>
 </ROW>
 <ROW>
  <SHOP_ID>7</SHOP_ID>
  <PHONE_NUMBER>+86 (491) 468-8410</PHONE_NUMBER>
  <SHOP_NAME>MISAKO</SHOP_NAME>
 </ROW>
 <ROW>
  <SHOP_ID>8</SHOP_ID>
  <PHONE_NUMBER>+33 (238) 228-8459</PHONE_NUMBER>
  <SHOP_NAME>PRIVALIA</SHOP_NAME>
 </ROW>
 <ROW>
  <SHOP_ID>9</SHOP_ID>
  <PHONE_NUMBER>+62 (628) 724-2072</PHONE_NUMBER>
  <SHOP_NAME>KIABI</SHOP_NAME>
 </ROW>
 <ROW>
  <SHOP_ID>10</SHOP_ID>
  <PHONE_NUMBER>+30 (864) 611-7113</PHONE_NUMBER>
  <SHOP_NAME>ZACARIS</SHOP_NAME>
 </ROW>
 <ROW>
  <SHOP_ID>11</SHOP_ID>
  <PHONE_NUMBER>+86 (461) 362-7274</PHONE_NUMBER>
  <SHOP_NAME>SPORTSDIRECT</SHOP_NAME>
 </ROW>
 <ROW>
  <SHOP_ID>12</SHOP_ID>
  <PHONE_NUMBER>+57 (937) 970-4413</PHONE_NUMBER>
  <SHOP_NAME>SECRET SALES</SHOP_NAME>
 </ROW>
 <ROW>
  <SHOP_ID>13</SHOP_ID>
  <PHONE_NUMBER>+84 (742) 547-2458</PHONE_NUMBER>
  <SHOP_NAME>FRAGRANCEDIRECT</SHOP_NAME>
 </ROW>
 <ROW>
  <SHOP_ID>14</SHOP_ID>
  <PHONE_NUMBER>+1 (272) 262-7318</PHONE_NUMBER>
  <SHOP_NAME>GAP</SHOP_NAME>
 </ROW>
 <ROW>
  <SHOP_ID>15</SHOP_ID>
  <PHONE_NUMBER>+55 (257) 604-4107</PHONE_NUMBER>
  <SHOP_NAME>THE OUTNET</SHOP_NAME>
 </ROW>
 <ROW>
  <SHOP_ID>16</SHOP_ID>
  <PHONE_NUMBER>+7 (530) 831-2319</PHONE_NUMBER>
  <SHOP_NAME>EBAY</SHOP_NAME>
 </ROW>
 <ROW>
  <SHOP_ID>17</SHOP_ID>
  <PHONE_NUMBER>+81 (762) 297-4054</PHONE_NUMBER>
  <SHOP_NAME>OTTO</SHOP_NAME>
 </ROW>
 <ROW>
  <SHOP_ID>18</SHOP_ID>
  <PHONE_NUMBER>+7 (575) 379-2730</PHONE_NUMBER>
  <SHOP_NAME>APART FASHION</SHOP_NAME>
 </ROW>
 <ROW>
  <SHOP_ID>19</SHOP_ID>
  <PHONE_NUMBER>+86 (369) 183-2909</PHONE_NUMBER>
  <SHOP_NAME>AMAZON</SHOP_NAME>
 </ROW>
 <ROW>
  <SHOP_ID>20</SHOP_ID>
  <PHONE_NUMBER>+255 (119) 699-1783</PHONE_NUMBER>
  <SHOP_NAME>BABY WALTZ</SHOP_NAME>
 </ROW>
 <ROW>
  <SHOP_ID>21</SHOP_ID>
  <PHONE_NUMBER>+86 (969) 664-5301</PHONE_NUMBER>
  <SHOP_NAME>ATTESA</SHOP_NAME>
 </ROW>
 <ROW>
  <SHOP_ID>22</SHOP_ID>
  <PHONE_NUMBER>+351 (260) 338-2098</PHONE_NUMBER>
  <SHOP_NAME>KIKKI LINE</SHOP_NAME>
 </ROW>
 <ROW>
  <SHOP_ID>23</SHOP_ID>
  <PHONE_NUMBER>+63 (384) 768-5942</PHONE_NUMBER>
  <SHOP_NAME>SPARTOO</SHOP_NAME>
 </ROW>
 <ROW>
  <SHOP_ID>24</SHOP_ID>
  <PHONE_NUMBER>+995 (203) 376-0699</PHONE_NUMBER>
  <SHOP_NAME>KIKO MILANO</SHOP_NAME>
 </ROW>
 <ROW>
  <SHOP_ID>25</SHOP_ID>
  <PHONE_NUMBER>+98 (528) 164-0647</PHONE_NUMBER>
  <SHOP_NAME>YOOX</SHOP_NAME>
 </ROW>
 <ROW>
  <SHOP_ID>26</SHOP_ID>
  <PHONE_NUMBER>+86 (964) 660-7539</PHONE_NUMBER>
  <SHOP_NAME>MODZ</SHOP_NAME>
 </ROW>
 <ROW>
  <SHOP_ID>27</SHOP_ID>
  <PHONE_NUMBER>+223 (660) 279-7534</PHONE_NUMBER>
  <SHOP_NAME>MISS COQUINES</SHOP_NAME>
 </ROW>
 <ROW>
  <SHOP_ID>28</SHOP_ID>
  <PHONE_NUMBER>+373 (239) 392-6234</PHONE_NUMBER>
  <SHOP_NAME>LA REDOUTE</SHOP_NAME>
 </ROW>
 <ROW>
  <SHOP_ID>29</SHOP_ID>
  <PHONE_NUMBER>+1 (305) 554-8583</PHONE_NUMBER>
  <SHOP_NAME>LA HALLE</SHOP_NAME>
 </ROW>
 <ROW>
  <SHOP_ID>30</SHOP_ID>
  <PHONE_NUMBER>+386 (507) 381-6957</PHONE_NUMBER>
  <SHOP_NAME>TATI</SHOP_NAME>
 </ROW>
 <ROW>
  <SHOP_ID>31</SHOP_ID>
  <PHONE_NUMBER>+55 (673) 968-8724</PHONE_NUMBER>
  <SHOP_NAME>SHOE TEC</SHOP_NAME>
 </ROW>
 <ROW>
  <SHOP_ID>32</SHOP_ID>
  <PHONE_NUMBER>+27 (256) 760-0682</PHONE_NUMBER>
  <SHOP_NAME>EFOR</SHOP_NAME>
 </ROW>
 <ROW>
  <SHOP_ID>33</SHOP_ID>
  <PHONE_NUMBER>+62 (113) 646-9223</PHONE_NUMBER>
  <SHOP_NAME>ADZE</SHOP_NAME>
 </ROW>
 <ROW>
  <SHOP_ID>34</SHOP_ID>
  <PHONE_NUMBER>+355 (910) 770-9185</PHONE_NUMBER>
  <SHOP_NAME>SARAR</SHOP_NAME>
 </ROW>
 <ROW>
  <SHOP_ID>35</SHOP_ID>
  <PHONE_NUMBER>+62 (256) 506-5090</PHONE_NUMBER>
  <SHOP_NAME>DAGI</SHOP_NAME>
 </ROW>
 <ROW>
  <SHOP_ID>36</SHOP_ID>
  <PHONE_NUMBER>+54 (720) 304-0320</PHONE_NUMBER>
  <SHOP_NAME>ELNINO.CZ</SHOP_NAME>
 </ROW>
 <ROW>
  <SHOP_ID>37</SHOP_ID>
  <PHONE_NUMBER>+62 (988) 322-1050</PHONE_NUMBER>
  <SHOP_NAME>OUTLET EXPERT</SHOP_NAME>
 </ROW>
 <ROW>
  <SHOP_ID>38</SHOP_ID>
  <PHONE_NUMBER>+48 (999) 618-8961</PHONE_NUMBER>
  <SHOP_NAME>TOPGAL</SHOP_NAME>
 </ROW>
 <ROW>
  <SHOP_ID>39</SHOP_ID>
  <PHONE_NUMBER>+94 (147) 407-1490</PHONE_NUMBER>
  <SHOP_NAME>DESIGUAL</SHOP_NAME>
 </ROW>
 <ROW>
  <SHOP_ID>40</SHOP_ID>
  <PHONE_NUMBER>+51 (514) 348-4340</PHONE_NUMBER>
  <SHOP_NAME>ALZA</SHOP_NAME>
 </ROW>
 <ROW>
  <SHOP_ID>41</SHOP_ID>
  <PHONE_NUMBER>+86 (654) 876-7884</PHONE_NUMBER>
  <SHOP_NAME>ASOS</SHOP_NAME>
 </ROW>
 <ROW>
  <SHOP_ID>42</SHOP_ID>
  <PHONE_NUMBER>+54 (646) 939-5503</PHONE_NUMBER>
  <SHOP_NAME>eBay.com</SHOP_NAME>
 </ROW>
 <ROW>
  <SHOP_ID>43</SHOP_ID>
  <PHONE_NUMBER>+30 (652) 389-3292</PHONE_NUMBER>
  <SHOP_NAME>GAP</SHOP_NAME>
 </ROW>
 <ROW>
  <SHOP_ID>44</SHOP_ID>
  <PHONE_NUMBER>+256 (554) 857-2506</PHONE_NUMBER>
  <SHOP_NAME>GAP Factory</SHOP_NAME>
 </ROW>
 <ROW>
  <SHOP_ID>45</SHOP_ID>
  <PHONE_NUMBER>+385 (345) 792-6846</PHONE_NUMBER>
  <SHOP_NAME>Walmart</SHOP_NAME>
 </ROW>
 <ROW>
  <SHOP_ID>46</SHOP_ID>
  <PHONE_NUMBER>+966 (363) 495-6784</PHONE_NUMBER>
  <SHOP_NAME>NEW LOOK</SHOP_NAME>
 </ROW>
 <ROW>
  <SHOP_ID>47</SHOP_ID>
  <PHONE_NUMBER>+7 (777) 188-4749</PHONE_NUMBER>
  <SHOP_NAME>Calvin Klein</SHOP_NAME>
 </ROW>
 <ROW>
  <SHOP_ID>48</SHOP_ID>
  <PHONE_NUMBER>+254 (757) 147-3109</PHONE_NUMBER>
  <SHOP_NAME>6pm</SHOP_NAME>
 </ROW>
 <ROW>
  <SHOP_ID>49</SHOP_ID>
  <PHONE_NUMBER>+385 (659) 323-2222</PHONE_NUMBER>
  <SHOP_NAME>Apple</SHOP_NAME>
 </ROW>
 <ROW>
  <SHOP_ID>50</SHOP_ID>
  <PHONE_NUMBER>+62 (896) 965-2494</PHONE_NUMBER>
  <SHOP_NAME>Extra Room</SHOP_NAME>
 </ROW>
 <ROW>
  <SHOP_ID>51</SHOP_ID>
  <PHONE_NUMBER>+376 (702) 868-1351</PHONE_NUMBER>
  <SHOP_NAME>Precise Store</SHOP_NAME>
 </ROW>
 <ROW>
  <SHOP_ID>52</SHOP_ID>
  <PHONE_NUMBER>+51 (941) 439-4829</PHONE_NUMBER>
  <SHOP_NAME>Springoo</SHOP_NAME>
 </ROW>
 <ROW>
  <SHOP_ID>53</SHOP_ID>
  <PHONE_NUMBER>+86 (463) 995-6017</PHONE_NUMBER>
  <SHOP_NAME>Scafe</SHOP_NAME>
 </ROW>
 <ROW>
  <SHOP_ID>54</SHOP_ID>
  <PHONE_NUMBER>+81 (781) 546-3388</PHONE_NUMBER>
  <SHOP_NAME>Lifestyle Store</SHOP_NAME>
 </ROW>
 <ROW>
  <SHOP_ID>55</SHOP_ID>
  <PHONE_NUMBER>+86 (789) 780-7186</PHONE_NUMBER>
  <SHOP_NAME>Breaking Point</SHOP_NAME>
 </ROW>
 <ROW>
  <SHOP_ID>56</SHOP_ID>
  <PHONE_NUMBER>+31 (876) 874-0146</PHONE_NUMBER>
  <SHOP_NAME>Unique Spot</SHOP_NAME>
 </ROW>
 <ROW>
  <SHOP_ID>57</SHOP_ID>
  <PHONE_NUMBER>+420 (239) 917-6247</PHONE_NUMBER>
  <SHOP_NAME>Glam Scape</SHOP_NAME>
 </ROW>
 <ROW>
  <SHOP_ID>58</SHOP_ID>
  <PHONE_NUMBER>+968 (463) 195-1922</PHONE_NUMBER>
  <SHOP_NAME>Chefly</SHOP_NAME>
 </ROW>
 <ROW>
  <SHOP_ID>59</SHOP_ID>
  <PHONE_NUMBER>+381 (165) 901-5954</PHONE_NUMBER>
  <SHOP_NAME>Beauty Deck</SHOP_NAME>
 </ROW>
 <ROW>
  <SHOP_ID>60</SHOP_ID>
  <PHONE_NUMBER>+86 (384) 249-9322</PHONE_NUMBER>
  <SHOP_NAME>Diva Lab</SHOP_NAME>
 </ROW>
 <ROW>
  <SHOP_ID>61</SHOP_ID>
  <PHONE_NUMBER>+353 (937) 123-3321</PHONE_NUMBER>
  <SHOP_NAME>Lace Press</SHOP_NAME>
 </ROW>
 <ROW>
  <SHOP_ID>62</SHOP_ID>
  <PHONE_NUMBER>+51 (207) 643-9691</PHONE_NUMBER>
  <SHOP_NAME>Keeper Store</SHOP_NAME>
 </ROW>
 <ROW>
  <SHOP_ID>63</SHOP_ID>
  <PHONE_NUMBER>+1 (808) 147-8277</PHONE_NUMBER>
  <SHOP_NAME>Olive You</SHOP_NAME>
 </ROW>
 <ROW>
  <SHOP_ID>64</SHOP_ID>
  <PHONE_NUMBER>+386 (530) 223-6488</PHONE_NUMBER>
  <SHOP_NAME>Southpointe Imports</SHOP_NAME>
 </ROW>
 <ROW>
  <SHOP_ID>65</SHOP_ID>
  <PHONE_NUMBER>+55 (326) 813-3628</PHONE_NUMBER>
  <SHOP_NAME>ForLife Store</SHOP_NAME>
 </ROW>
 <ROW>
  <SHOP_ID>66</SHOP_ID>
  <PHONE_NUMBER>+254 (881) 961-2892</PHONE_NUMBER>
  <SHOP_NAME>Maxim’s Outlet</SHOP_NAME>
 </ROW>
 <ROW>
  <SHOP_ID>67</SHOP_ID>
  <PHONE_NUMBER>+86 (463) 449-4029</PHONE_NUMBER>
  <SHOP_NAME>Style Shack</SHOP_NAME>
 </ROW>
 <ROW>
  <SHOP_ID>68</SHOP_ID>
  <PHONE_NUMBER>+7 (192) 479-7855</PHONE_NUMBER>
  <SHOP_NAME>Heel’s Heaven</SHOP_NAME>
 </ROW>
 <ROW>
  <SHOP_ID>69</SHOP_ID>
  <PHONE_NUMBER>+57 (630) 234-7408</PHONE_NUMBER>
  <SHOP_NAME>Healthy Store</SHOP_NAME>
 </ROW>
 <ROW>
  <SHOP_ID>70</SHOP_ID>
  <PHONE_NUMBER>+86 (219) 792-9090</PHONE_NUMBER>
  <SHOP_NAME>Europe Shop</SHOP_NAME>
 </ROW>
 <ROW>
  <SHOP_ID>71</SHOP_ID>
  <PHONE_NUMBER>+86 (923) 885-2148</PHONE_NUMBER>
  <SHOP_NAME>Pet Studio</SHOP_NAME>
 </ROW>
 <ROW>
  <SHOP_ID>72</SHOP_ID>
  <PHONE_NUMBER>+506 (557) 616-7670</PHONE_NUMBER>
  <SHOP_NAME>Store Graph</SHOP_NAME>
 </ROW>
 <ROW>
  <SHOP_ID>73</SHOP_ID>
  <PHONE_NUMBER>+48 (754) 930-1081</PHONE_NUMBER>
  <SHOP_NAME>The Clean Wraith</SHOP_NAME>
 </ROW>
 <ROW>
  <SHOP_ID>74</SHOP_ID>
  <PHONE_NUMBER>+370 (146) 854-9091</PHONE_NUMBER>
  <SHOP_NAME>Sale Connection</SHOP_NAME>
 </ROW>
 <ROW>
  <SHOP_ID>75</SHOP_ID>
  <PHONE_NUMBER>+7 (448) 457-6362</PHONE_NUMBER>
  <SHOP_NAME>Bark &amp; Beauty</SHOP_NAME>
 </ROW>
 <ROW>
  <SHOP_ID>76</SHOP_ID>
  <PHONE_NUMBER>+970 (783) 859-6013</PHONE_NUMBER>
  <SHOP_NAME>Store Rule</SHOP_NAME>
 </ROW>
 <ROW>
  <SHOP_ID>77</SHOP_ID>
  <PHONE_NUMBER>+48 (790) 191-9735</PHONE_NUMBER>
  <SHOP_NAME>Nirvana Elegance</SHOP_NAME>
 </ROW>
 <ROW>
  <SHOP_ID>78</SHOP_ID>
  <PHONE_NUMBER>+389 (400) 968-9546</PHONE_NUMBER>
  <SHOP_NAME>Cake It Easy</SHOP_NAME>
 </ROW>
 <ROW>
  <SHOP_ID>79</SHOP_ID>
  <PHONE_NUMBER>+351 (244) 541-9447</PHONE_NUMBER>
  <SHOP_NAME>Real Diva</SHOP_NAME>
 </ROW>
 <ROW>
  <SHOP_ID>80</SHOP_ID>
  <PHONE_NUMBER>+385 (494) 245-4674</PHONE_NUMBER>
  <SHOP_NAME>Pane in the Glass</SHOP_NAME>
 </ROW>
 <ROW>
  <SHOP_ID>81</SHOP_ID>
  <PHONE_NUMBER>+98 (921) 767-2750</PHONE_NUMBER>
  <SHOP_NAME>Axial Store</SHOP_NAME>
 </ROW>
 <ROW>
  <SHOP_ID>82</SHOP_ID>
  <PHONE_NUMBER>+63 (709) 578-9640</PHONE_NUMBER>
  <SHOP_NAME>Apple Grand Central</SHOP_NAME>
 </ROW>
 <ROW>
  <SHOP_ID>83</SHOP_ID>
  <PHONE_NUMBER>+66 (915) 380-3111</PHONE_NUMBER>
  <SHOP_NAME>Store Directory</SHOP_NAME>
 </ROW>
 <ROW>
  <SHOP_ID>84</SHOP_ID>
  <PHONE_NUMBER>+58 (648) 776-9489</PHONE_NUMBER>
  <SHOP_NAME>Visionstore</SHOP_NAME>
 </ROW>
 <ROW>
  <SHOP_ID>85</SHOP_ID>
  <PHONE_NUMBER>+63 (563) 170-8056</PHONE_NUMBER>
  <SHOP_NAME>FashionFiesta</SHOP_NAME>
 </ROW>
 <ROW>
  <SHOP_ID>86</SHOP_ID>
  <PHONE_NUMBER>+231 (661) 996-7322</PHONE_NUMBER>
  <SHOP_NAME>Anytime Buys</SHOP_NAME>
 </ROW>
 <ROW>
  <SHOP_ID>87</SHOP_ID>
  <PHONE_NUMBER>+86 (396) 551-9861</PHONE_NUMBER>
  <SHOP_NAME>The Earnest Pen Garden Center</SHOP_NAME>
 </ROW>
 <ROW>
  <SHOP_ID>88</SHOP_ID>
  <PHONE_NUMBER>+63 (919) 546-8892</PHONE_NUMBER>
  <SHOP_NAME>Nondescript Things</SHOP_NAME>
 </ROW>
 <ROW>
  <SHOP_ID>89</SHOP_ID>
  <PHONE_NUMBER>+351 (289) 612-5077</PHONE_NUMBER>
  <SHOP_NAME>The Angelic Growth</SHOP_NAME>
 </ROW>
 <ROW>
  <SHOP_ID>90</SHOP_ID>
  <PHONE_NUMBER>+31 (991) 684-8510</PHONE_NUMBER>
  <SHOP_NAME>Pixel Store</SHOP_NAME>
 </ROW>
 <ROW>
  <SHOP_ID>91</SHOP_ID>
  <PHONE_NUMBER>+55 (502) 424-7434</PHONE_NUMBER>
  <SHOP_NAME>Renew Store</SHOP_NAME>
 </ROW>
 <ROW>
  <SHOP_ID>92</SHOP_ID>
  <PHONE_NUMBER>+351 (559) 800-4469</PHONE_NUMBER>
  <SHOP_NAME>Best Of The Earth</SHOP_NAME>
 </ROW>
 <ROW>
  <SHOP_ID>93</SHOP_ID>
  <PHONE_NUMBER>+86 (535) 181-3573</PHONE_NUMBER>
  <SHOP_NAME>Primose Beauty Products</SHOP_NAME>
 </ROW>
 <ROW>
  <SHOP_ID>94</SHOP_ID>
  <PHONE_NUMBER>+229 (407) 532-3430</PHONE_NUMBER>
  <SHOP_NAME>Glow Inc</SHOP_NAME>
 </ROW>
 <ROW>
  <SHOP_ID>95</SHOP_ID>
  <PHONE_NUMBER>+62 (164) 675-9944</PHONE_NUMBER>
  <SHOP_NAME>Eclipse Spa</SHOP_NAME>
 </ROW>
 <ROW>
  <SHOP_ID>96</SHOP_ID>
  <PHONE_NUMBER>+55 (476) 350-8011</PHONE_NUMBER>
  <SHOP_NAME>The Everything Shop</SHOP_NAME>
 </ROW>
 <ROW>
  <SHOP_ID>97</SHOP_ID>
  <PHONE_NUMBER>+7 (471) 258-2954</PHONE_NUMBER>
  <SHOP_NAME>Store Junky</SHOP_NAME>
 </ROW>
 <ROW>
  <SHOP_ID>98</SHOP_ID>
  <PHONE_NUMBER>+62 (749) 936-7904</PHONE_NUMBER>
  <SHOP_NAME>Dream Store</SHOP_NAME>
 </ROW>
 <ROW>
  <SHOP_ID>99</SHOP_ID>
  <PHONE_NUMBER>+54 (610) 173-2854</PHONE_NUMBER>
  <SHOP_NAME>Happiness Store</SHOP_NAME>
 </ROW>
 <ROW>
  <SHOP_ID>100</SHOP_ID>
  <PHONE_NUMBER>+98 (623) 949-8895</PHONE_NUMBER>
  <SHOP_NAME>LG</SHOP_NAME>
 </ROW>
</ROWSET>
